greap/__init__.py
greap/api.py
greap/cache.py
greap/constants.py
greap/db.py
greap/diff_subscriber.py
greap/exceptions.py
greap/import_utils.py
greap/models.py
greap/profiler.py
greap/timer.py
greap/types.py
greap/backtest/__init__.py
greap/backtest/backtest.py
greap/cli/__init__.py
greap/cli/patch.py
greap/clients/__init__.py
greap/clients/alpaca.py
greap/clients/backtest.py
greap/clients/commons.py
greap/clients/factory.py
greap/clients/utils.py
greap/clients/wb.py
greap/docker/__init__.py
greap/docker/builder.py
greap/docker/template.Dockerfile
greap/immortals/__init__.py
greap/immortals/backtest_quote_price_feeder.py
greap/immortals/base.py
greap/immortals/connector.py
greap/immortals/controller.py
greap/immortals/event.py
greap/immortals/factory.py
greap/immortals/load_balancer.py
greap/immortals/prefetcher.py
greap/immortals/server.py
greap/immortals/test_data.py
greap/immortals/validator.py
greap/immortals/signals/__init__.py
greap/logger/__init__.py
greap/logger/logger.py
greap/logger/rich_utils.py
greap/math/utils.py
greap/numba/optimize.py
greap/spawner/__init__.py
greap/spawner/address_pool.py
greap/spawner/docker.py
greap/spawner/k8s.py
greap/spawner/lib.py
greap/spawner/mp.py
greap/zmq/socket.py
greap-0.0.2rc2.dist-info/entry_points.txt
greap-0.0.2rc2.dist-info/LICENSE
greap-0.0.2rc2.dist-info/WHEEL
greap-0.0.2rc2.dist-info/METADATA
greap-0.0.2rc2.dist-info/RECORD
