Metadata-Version: 2.1
Name: greap
Version: 0.0.2rc2
Summary: Trading Library
Author-email: Greap <winston@greap.trade>
Requires-Python: >=3.8
Classifier: Intended Audience :: Information Technology
Classifier: Operating System :: OS Independent
Classifier: Programming Language :: Python :: 3
Classifier: Programming Language :: Python
Classifier: Topic :: Internet
Classifier: Topic :: Software Development :: Libraries :: Python Modules
Classifier: Topic :: Software Development :: Libraries
Classifier: Topic :: Software Development
Classifier: Typing :: Typed
Classifier: Development Status :: 4 - Beta
Classifier: Environment :: Web Environment
Classifier: Framework :: AsyncIO
Classifier: License :: OSI Approved :: GNU General Public License v3 (GPLv3)
Classifier: Programming Language :: Python :: 3 :: Only
Classifier: Programming Language :: Python :: 3.6
Classifier: Programming Language :: Python :: 3.7
Classifier: Programming Language :: Python :: 3.8
Classifier: Programming Language :: Python :: 3.9
Requires-Dist: rich
Requires-Dist: aiohttp
Requires-Dist: zmq
Requires-Dist: pyyaml
Requires-Dist: bidict
Requires-Dist: aiosqlite
Requires-Dist: forbiddenfruit==0.1.4
Requires-Dist: uvloop
Requires-Dist: sqlmodel
Requires-Dist: loguru
Requires-Dist: pytz
Requires-Dist: numba
Requires-Dist: uvicorn ==0.17.0
Requires-Dist: fastapi
Requires-Dist: asyncer
Requires-Dist: webull
Requires-Dist: greenlet
Requires-Dist: asyncio-mqtt
Requires-Dist: pre-commit
Requires-Dist: orjson
Requires-Dist: typeguard
Requires-Dist: docker
Requires-Dist: pyRFC3339
Requires-Dist: alpaca-trade-api
Requires-Dist: dictdiffer
Requires-Dist: pwinput
Requires-Dist: mysqlclient
Requires-Dist: sqlalchemy-utils
Requires-Dist: aiomysql
Requires-Dist: mypy ==0.910 ; extra == "dev"
Requires-Dist: flake8 >=3.8.3,<4.0.0 ; extra == "dev"
Requires-Dist: black ==21.9b0 ; extra == "dev"
Requires-Dist: isort >=5.0.6,<6.0.0 ; extra == "dev"
Requires-Dist: pytest >=6.2.4,<7.0.0 ; extra == "dev"
Requires-Dist: pytest-cov >=2.12.0,<4.0.0 ; extra == "dev"
Requires-Dist: pytest-xdist ; extra == "dev"
Requires-Dist: pytest-asyncio ; extra == "dev"
Requires-Dist: pytest-reraise ; extra == "dev"
Requires-Dist: pytest-mock ; extra == "dev"
Requires-Dist: mkdocs >=1.1.2,<2.0.0 ; extra == "dev"
Requires-Dist: mkdocs-material >=7.1.9,<8.0.0 ; extra == "dev"
Requires-Dist: jinja2>=2.11.1 ; extra == "dev"
Requires-Dist: mkdocs >=1.1.2,<2.0.0 ; extra == "docs"
Requires-Dist: mkdocs-material >=7.1.9,<8.0.0 ; extra == "docs"
Requires-Dist: mkdocstrings ; extra == "docs"
Requires-Dist: jinja2>=2.11.1 ; extra == "docs"
Project-URL: Source, https://github.com/greaphello/greap
Provides-Extra: dev
Provides-Extra: docs
